dk_azure_services/__init__.py
dk_azure_services/blob_storage/__init__.py
dk_azure_services/blob_storage/async_blob_storage.py
dk_azure_services/blob_storage/secrets.py
dk_azure_services/common/__init__.py
dk_azure_services/common/auth.py
dk_azure_services/common/config.py
dk_azure_services/common/exceptions.py
dk_azure_services/cosmos/__init__.py
dk_azure_services/cosmos/container_manager.py
dk_azure_services/cosmos/database_manager.py
dk_azure_services/cosmos/documents_manager.py
dk_azure_services/cosmos/simple_client.py
dk_azure_services/datalake/__init__.py
dk_azure_services/datalake/async_datalake.py
dk_azure_services/searchai/_init_.py
dk_azure_services/searchai/async_search.py
dk_azure_services_dataknow-0.0.41.dist-info/METADATA
dk_azure_services_dataknow-0.0.41.dist-info/WHEEL
dk_azure_services_dataknow-0.0.41.dist-info/top_level.txt
dk_azure_services_dataknow-0.0.41.dist-info/RECORD
