Metadata-Version: 2.4
Name: dk-azure-services-dataknow
Version: 0.0.41
Summary: Paquete para facilitar la integración con servicios de Azure
Author-email: Leonar Santiago Castro <leonar.castro@dataknow.co>
License-Expression: MIT
Project-URL: Homepage, https://dataknow.io/
Project-URL: Documentation, https://dev.azure.com/DataKnow/Dataknow%20-%20Repositorio%20General%20de%20Proyectos/_wiki/wikis/Dataknow---Repositorio-General-de-Proyectos.wiki/7/DK-Azure-Service-Package
Project-URL: Repository, https://dev.azure.com/DataKnow/Dataknow%20-%20Repositorio%20General%20de%20Proyectos/_git/dk-azure-services
Keywords: azure,cosmos,storage,keyvault,datalake,search
Classifier: Development Status :: 3 - Alpha
Classifier: Intended Audience :: Developers
Classifier: Programming Language :: Python :: 3
Classifier: Programming Language :: Python :: 3.8
Classifier: Programming Language :: Python :: 3.9
Classifier: Programming Language :: Python :: 3.10
Classifier: Programming Language :: Python :: 3.11
Classifier: Topic :: Software Development :: Libraries :: Python Modules
Classifier: Topic :: Internet :: WWW/HTTP :: Dynamic Content
Classifier: Topic :: Database
Requires-Python: >=3.8
Requires-Dist: azure-identity[aio]>=1.15.0
Requires-Dist: azure-cosmos>=4.5.0
Requires-Dist: azure-keyvault-secrets>=4.7.0
Requires-Dist: azure-storage-blob>=12.25.1
Requires-Dist: azure-storage-file-datalake==12.20.0
Requires-Dist: azure-search-documents==11.5.3
Requires-Dist: pandas>=2.3.1
Requires-Dist: python-dotenv>=1.0.0
Requires-Dist: typing-extensions>=4.0.0
Requires-Dist: aiohttp>=3.8.0
Provides-Extra: dev
Requires-Dist: pytest>=7.0.0; extra == "dev"
Requires-Dist: pytest-asyncio>=0.21.0; extra == "dev"
Requires-Dist: pytest-cov>=4.0.0; extra == "dev"
Requires-Dist: black>=23.0.0; extra == "dev"
Requires-Dist: isort>=5.12.0; extra == "dev"
Requires-Dist: flake8>=6.0.0; extra == "dev"
Requires-Dist: mypy>=1.0.0; extra == "dev"
Provides-Extra: docs
Requires-Dist: sphinx>=5.0.0; extra == "docs"
Requires-Dist: sphinx-rtd-theme>=1.2.0; extra == "docs"
